TM_CommonPy/CommandSet.py
TM_CommonPy/CopyContext.py
TM_CommonPy/ElementTreeContext.py
TM_CommonPy/Misc.py
TM_CommonPy/Narrator.py
TM_CommonPy/WorkspaceContext.py
TM_CommonPy/_Logger.py
TM_CommonPy/__init__.py
TM_CommonPy-1.0.1.dist-info/METADATA
TM_CommonPy-1.0.1.dist-info/RECORD
TM_CommonPy-1.0.1.dist-info/WHEEL
TM_CommonPy-1.0.1.dist-info/top_level.txt
