Metadata-Version: 2.1
Name: TM-CommonPy
Version: 1.0.1
Summary: Troy1010's common python library
Home-page: https://github.com/Troy1010/TM_CommonPy
Author: Troy1010
License: MIT
Platform: UNKNOWN
Requires-Python: >=3.6
Requires-Dist: dill
Requires-Dist: openpyxl
